senaite.api-1.2.3.post2-py2.7-nspkg.pth
senaite/.DS_Store
senaite/api/.DS_Store
senaite/api/__init__.py
senaite/api/analysis.py
senaite/api/configure.zcml
senaite/api/docs/.DS_Store
senaite/api/docs/API.rst
senaite/api/docs/API_analysis.rst
senaite/api/tests/__init__.py
senaite/api/tests/base.py
senaite/api/tests/test_doctests.py
senaite/api/tests/test_setup.py
senaite.api-1.2.3.post2.dist-info/METADATA
senaite.api-1.2.3.post2.dist-info/RECORD
senaite.api-1.2.3.post2.dist-info/WHEEL
senaite.api-1.2.3.post2.dist-info/entry_points.txt
senaite.api-1.2.3.post2.dist-info/namespace_packages.txt
senaite.api-1.2.3.post2.dist-info/top_level.txt
