Metadata-Version: 2.1
Name: senaite.api
Version: 1.2.3.post2
Summary: SENAITE API
Home-page: https://github.com/senaite/senaite.api
Author: SENAITE Foundation
Author-email: hello@senaite.com
License: GPLv2
Platform: UNKNOWN
Classifier: Programming Language :: Python
Classifier: Framework :: Plone
Classifier: Framework :: Zope2
Provides-Extra: test
Requires-Dist: setuptools
Requires-Dist: plone.api
Requires-Dist: senaite.core
Provides-Extra: test
Requires-Dist: Products.PloneTestCase; extra == 'test'
Requires-Dist: Products.SecureMailHost; extra == 'test'
Requires-Dist: plone.app.robotframework; extra == 'test'
Requires-Dist: plone.app.testing; extra == 'test'
Requires-Dist: robotframework-debuglibrary; extra == 'test'
Requires-Dist: robotframework-selenium2library; extra == 'test'
Requires-Dist: robotsuite; extra == 'test'
Requires-Dist: unittest2; extra == 'test'
